{
  "name": "Pahang",
  "city": [
    {
      "name": "Balok",
      "postcode": ["26080", "26100", "26150", "26190"]
    },
    {
      "name": "Bandar Pusat  Jengka",
      "postcode": [
        "26400",
        "26410",
        "26420",
        "26430",
        "26440",
        "26450",
        "26460",
        "26485",
        "26490",
        "27080"
      ]
    },
    {
      "name": "Bandar Tun Abdul Razak",
      "postcode": ["26900", "26999"]
    },
    {
      "name": "Benta",
      "postcode": ["27300", "27310"]
    },
    {
      "name": "Bentong",
      "postcode": ["28700", "28707", "28709", "28730", "28740", "28750"]
    },
    {
      "name": "Brinchang",
      "postcode": ["39100"]
    },
    {
      "name": "Bukit Fraser",
      "postcode": ["49000"]
    },
    {
      "name": "Bukit Goh",
      "postcode": ["26050", "26090"]
    },
    {
      "name": "Chenor",
      "postcode": ["28100"]
    },
    {
      "name": "Chini",
      "postcode": ["26690"]
    },
    {
      "name": "Damak",
      "postcode": ["27030"]
    },
    {
      "name": "Dong",
      "postcode": ["27400"]
    },
    {
      "name": "Gambang",
      "postcode": [
        "26300",
        "26310",
        "26320",
        "26330",
        "26340",
        "26350",
        "26360",
        "26370"
      ]
    },
    {
      "name": "Genting Highlands",
      "postcode": ["69000"]
    },
    {
      "name": "Jaya Gading",
      "postcode": ["26250"]
    },
    {
      "name": "Jerantut",
      "postcode": [
        "27000",
        "27010",
        "27020",
        "27040",
        "27050",
        "27060",
        "27070",
        "27090",
        "27150"
      ]
    },
    {
      "name": "Karak",
      "postcode": ["28600", "28610", "28620"]
    },
    {
      "name": "Kemayan",
      "postcode": ["28340", "28380"]
    },
    {
      "name": "Kuala Krau",
      "postcode": ["28050"]
    },
    {
      "name": "Kuala Lipis",
      "postcode": ["27200", "27207", "27209", "27210"]
    },
    {
      "name": "Kuala Rompin",
      "postcode": ["26800", "26810", "26820"]
    },
    {
      "name": "Kuantan",
      "postcode": [
        "25000",
        "25020",
        "25040",
        "25050",
        "25100",
        "25150",
        "25200",
        "25250",
        "25300",
        "25320",
        "25350",
        "25500",
        "25502",
        "25503",
        "25504",
        "25505",
        "25506",
        "25508",
        "25509",
        "25512",
        "25514",
        "25516",
        "25517",
        "25518",
        "25520",
        "25524",
        "25529",
        "25532",
        "25534",
        "25536",
        "25538",
        "25540",
        "25546",
        "25548",
        "25550",
        "25551",
        "25552",
        "25556",
        "25558",
        "25560",
        "25564",
        "25570",
        "25576",
        "25578",
        "25582",
        "25584",
        "25586",
        "25590",
        "25592",
        "25594",
        "25596",
        "25598",
        "25600",
        "25604",
        "25606",
        "25608",
        "25609",
        "25610",
        "25612",
        "25614",
        "25620",
        "25622",
        "25626",
        "25628",
        "25630",
        "25632",
        "25644",
        "25646",
        "25648",
        "25656",
        "25660",
        "25661",
        "25662",
        "25670",
        "25672",
        "25673",
        "25674",
        "25676",
        "25690",
        "25700",
        "25710",
        "25720",
        "25730",
        "25740",
        "25750",
        "25990",
        "26000",
        "26010",
        "26040",
        "26060",
        "26070",
        "26140",
        "26180"
      ]
    },
    {
      "name": "Lanchang",
      "postcode": ["28500"]
    },
    {
      "name": "Lurah Bilut",
      "postcode": ["28800"]
    },
    {
      "name": "Maran",
      "postcode": ["26500"]
    },
    {
      "name": "Mentakab",
      "postcode": ["28400", "28407", "28409"]
    },
    {
      "name": "Muadzam Shah",
      "postcode": ["26700"]
    },
    {
      "name": "Padang Tengku",
      "postcode": ["27100"]
    },
    {
      "name": "Pekan",
      "postcode": [
        "26600",
        "26607",
        "26609",
        "26610",
        "26620",
        "26630",
        "26640",
        "26650",
        "26660",
        "26680"
      ]
    },
    {
      "name": "Raub",
      "postcode": [
        "27600",
        "27607",
        "27609",
        "27610",
        "27620",
        "27630",
        "27670"
      ]
    },
    {
      "name": "Ringlet",
      "postcode": ["39200"]
    },
    {
      "name": "Sega",
      "postcode": ["27660"]
    },
    {
      "name": "Sungai Koyan",
      "postcode": ["27650"]
    },
    {
      "name": "Sungai Lembing",
      "postcode": ["26200"]
    },
    {
      "name": "Sungai Ruan",
      "postcode": ["27500"]
    },
    {
      "name": "Tanah Rata",
      "postcode": ["39000", "39007", "39009", "39010"]
    },
    {
      "name": "Temerloh",
      "postcode": [
        "28000",
        "28007",
        "28009",
        "28010",
        "28020",
        "28030",
        "28040"
      ]
    },
    {
      "name": "Triang",
      "postcode": ["28200", "28300", "28310", "28320", "28330", "28350"]
    }
  ]
}
