{
  "name": "Selangor",
  "city": [
    {
      "name": "Ampang",
      "postcode": ["68000"]
    },
    {
      "name": "Bandar Baru Bangi",
      "postcode": ["43650"]
    },
    {
      "name": "Bandar Puncak Alam",
      "postcode": ["42300"]
    },
    {
      "name": "Bangi",
      "postcode": ["43600"]
    },
    {
      "name": "Banting",
      "postcode": ["42700"]
    },
    {
      "name": "Batang Berjuntai",
      "postcode": ["45600", "45607", "45609", "45620", "45630"]
    },
    {
      "name": "Batang Kali",
      "postcode": ["44300", "44309", "44330"]
    },
    {
      "name": "Batu Caves",
      "postcode": ["68100"]
    },
    {
      "name": "Beranang",
      "postcode": ["43700", "43701"]
    },
    {
      "name": "Bukit Rotan",
      "postcode": ["45700"]
    },
    {
      "name": "Cheras",
      "postcode": ["43200", "43207"]
    },
    {
      "name": "Cyberjaya",
      "postcode": ["63000", "63100", "63200", "63300"]
    },
    {
      "name": "Dengkil",
      "postcode": ["43800", "43807"]
    },
    {
      "name": "Hulu Langat",
      "postcode": ["43100"]
    },
    {
      "name": "Jenjarom",
      "postcode": ["42600", "42610", "42619"]
    },
    {
      "name": "Jeram",
      "postcode": ["45800"]
    },
    {
      "name": "Kajang",
      "postcode": ["43000", "43007", "43009", "43558"]
    },
    {
      "name": "Kapar",
      "postcode": ["42200", "42209"]
    },
    {
      "name": "Kerling",
      "postcode": ["44100"]
    },
    {
      "name": "Klang",
      "postcode": [
        "41000",
        "41050",
        "41070",
        "41100",
        "41150",
        "41160",
        "41200",
        "41205",
        "41250",
        "41299",
        "41300",
        "41301",
        "41400",
        "41500",
        "41506",
        "41560",
        "41586",
        "41600",
        "41670",
        "41672",
        "41700",
        "41710",
        "41720",
        "41730",
        "41750",
        "41780",
        "41900",
        "41902",
        "41904",
        "41906",
        "41908",
        "41910",
        "41912",
        "41914",
        "41916",
        "41918",
        "41990",
        "42100",
        "42150"
      ]
    },
    {
      "name": "Klia",
      "postcode": ["64000"]
    },
    {
      "name": "Kuala Kubu Baru",
      "postcode": ["44000", "44010", "44020", "44110"]
    },
    {
      "name": "Kuala Selangor",
      "postcode": ["45000", "45010"]
    },
    {
      "name": "Pelabuhan Klang",
      "postcode": ["42000", "42007", "42008", "42009"]
    },
    {
      "name": "Petaling Jaya",
      "postcode": [
        "46000",
        "46040",
        "46050",
        "46080",
        "46100",
        "46150",
        "46160",
        "46200",
        "46300",
        "46350",
        "46400",
        "46460",
        "46500",
        "46505",
        "46506",
        "46510",
        "46547",
        "46549",
        "46551",
        "46564",
        "46582",
        "46598",
        "46662",
        "46667",
        "46668",
        "46672",
        "46675",
        "46692",
        "46700",
        "46710",
        "46720",
        "46730",
        "46740",
        "46750",
        "46760",
        "46770",
        "46780",
        "46781",
        "46782",
        "46783",
        "46784",
        "46785",
        "46786",
        "46787",
        "46788",
        "46789",
        "46790",
        "46791",
        "46792",
        "46793",
        "46794",
        "46795",
        "46796",
        "46797",
        "46798",
        "46799",
        "46800",
        "46801",
        "46802",
        "46803",
        "46804",
        "46805",
        "46806",
        "46860",
        "46870",
        "46960",
        "46962",
        "46964",
        "46966",
        "46968",
        "46970",
        "46972",
        "46974",
        "46976",
        "46978",
        "46990",
        "47300",
        "47301",
        "47304",
        "47307",
        "47308",
        "47309",
        "47310",
        "47400",
        "47410",
        "47430",
        "47800",
        "47801",
        "47810",
        "47820",
        "47829",
        "47830",
        "47850"
      ]
    },
    {
      "name": "Puchong",
      "postcode": [
        "47100",
        "47110",
        "47120",
        "47130",
        "47140",
        "47150",
        "47160",
        "47170",
        "47180",
        "47190"
      ]
    },
    {
      "name": "Pulau Carey",
      "postcode": ["42960", "42999"]
    },
    {
      "name": "Pulau Indah",
      "postcode": ["42900", "42907", "42920"]
    },
    {
      "name": "Pulau Ketam",
      "postcode": ["42940"]
    },
    {
      "name": "Rasa",
      "postcode": ["44200"]
    },
    {
      "name": "Rawang",
      "postcode": [
        "48000",
        "48009",
        "48010",
        "48020",
        "48050",
        "48100",
        "48300",
        "48302"
      ]
    },
    {
      "name": "Sabak Bernam",
      "postcode": ["45200", "45207", "45209"]
    },
    {
      "name": "Sekinchan",
      "postcode": ["45400"]
    },
    {
      "name": "Semenyih",
      "postcode": ["43500"]
    },
    {
      "name": "Sepang",
      "postcode": ["43900"]
    },
    {
      "name": "Serdang",
      "postcode": ["43400"]
    },
    {
      "name": "Serendah",
      "postcode": ["48200", "48250"]
    },
    {
      "name": "Seri Kembangan",
      "postcode": ["43300", "43399"]
    },
    {
      "name": "Shah Alam",
      "postcode": [
        "40000",
        "40100",
        "40140",
        "40150",
        "40160",
        "40169",
        "40170",
        "40179",
        "40200",
        "40250",
        "40300",
        "40350",
        "40400",
        "40409",
        "40410",
        "40440",
        "40450",
        "40460",
        "40470",
        "40490",
        "40500",
        "40502",
        "40503",
        "40505",
        "40512",
        "40517",
        "40520",
        "40529",
        "40542",
        "40548",
        "40550",
        "40551",
        "40560",
        "40564",
        "40570",
        "40572",
        "40576",
        "40578",
        "40582",
        "40590",
        "40592",
        "40594",
        "40596",
        "40598",
        "40600",
        "40604",
        "40607",
        "40608",
        "40610",
        "40612",
        "40620",
        "40622",
        "40626",
        "40630",
        "40632",
        "40646",
        "40648",
        "40650",
        "40660",
        "40664",
        "40670",
        "40672",
        "40673",
        "40674",
        "40675",
        "40676",
        "40680",
        "40690",
        "40700",
        "40702",
        "40704",
        "40706",
        "40708",
        "40710",
        "40712",
        "40714",
        "40716",
        "40718",
        "40720",
        "40722",
        "40724",
        "40726",
        "40728",
        "40730",
        "40732",
        "40800",
        "40802",
        "40804",
        "40806",
        "40808",
        "40810",
        "40900",
        "40912",
        "40915",
        "40990",
        "42450"
      ]
    },
    {
      "name": "Subang Airport",
      "postcode": ["47200", "47210"]
    },
    {
      "name": "Subang Jaya",
      "postcode": [
        "47500",
        "47507",
        "47510",
        "47600",
        "47601",
        "47610",
        "47618",
        "47620",
        "47630",
        "47640",
        "47650",
        "55555"
      ]
    },
    {
      "name": "Sungai Ayer Tawar",
      "postcode": ["45100"]
    },
    {
      "name": "Sungai Besar",
      "postcode": ["45300"]
    },
    {
      "name": "Sungai Buloh",
      "postcode": ["47000", "47020", "47031"]
    },
    {
      "name": "Sungai Pelek",
      "postcode": ["43950", "43999"]
    },
    {
      "name": "Tanjong Karang",
      "postcode": ["45500"]
    },
    {
      "name": "Tanjong Sepat",
      "postcode": ["42800"]
    },
    {
      "name": "Telok Panglima Garang",
      "postcode": ["42425", "42500", "42507", "42509"]
    }
  ]
}
